kafkaclientveli/__init__.py
kafkaclientveli/consumer.py
kafkaclientveli/eventregistration.py
kafkaclientveli/exceptions.py
kafkaclientveli/producer.py
kafkaclientveli/events/__init__.py
kafkaclientveli/events/base.py
kafkaclientveli/events/triptracker.py
kafkaclientveli/topics/__init__.py
kafkaclientveli/topics/topics.py
kafkaclientveli/topics/triptracker.py
kafkaclientveli-1.0.15.dist-info/METADATA
kafkaclientveli-1.0.15.dist-info/WHEEL
kafkaclientveli-1.0.15.dist-info/top_level.txt
kafkaclientveli-1.0.15.dist-info/RECORD
