Metadata-Version: 2.1
Name: kafkaclientveli
Version: 1.0.15
Summary: Veli Kafka Client
Author: Konstantine
Author-email: kdvalishvili@veli.store
